{
  "boundaries": [
    [
      {
        "lat": 43.18065654180292,
        "lon": -72.10052233951491
      },
      {
        "lat": 43.18024189680457,
        "lon": -72.10026484744948
      },
      {
        "lat": 43.18021842624875,
        "lon": -72.09924560802382
      },
      {
        "lat": 43.18060960100106,
        "lon": -72.09789377468032
      },
      {
        "lat": 43.18149364670894,
        "lon": -72.09759336727065
      },
      {
        "lat": 43.18064871833845,
        "lon": -72.10050088184279
      }
    ]
  ],
  "id": "22-5-02"
}